kita/__init__.py
kita-1.1.0.dist-info/METADATA
kita-1.1.0.dist-info/WHEEL
kita-1.1.0.dist-info/top_level.txt
kita-1.1.0.dist-info/RECORD
