Metadata-Version: 2.4
Name: kita
Version: 1.1.0
Summary: Official Python SDK for Kita Document Processing API
Author-email: Kita Team <support@usekita.com>
Maintainer-email: Kita Team <support@usekita.com>
License: MIT
Project-URL: Homepage, https://usekita.com
Project-URL: Documentation, https://docs.usekita.com
Project-URL: Repository, https://github.com/usekita/kita-python-sdk
Project-URL: Issues, https://github.com/usekita/kita-python-sdk/issues
Project-URL: Changelog, https://github.com/usekita/kita-python-sdk/blob/main/CHANGELOG.md
Keywords: kita,document-processing,ocr,bank-statement,payslip,pdf,api,sdk
Classifier: Development Status :: 5 - Production/Stable
Classifier: Intended Audience :: Developers
Classifier: License :: OSI Approved :: MIT License
Classifier: Operating System :: OS Independent
Classifier: Programming Language :: Python :: 3
Classifier: Programming Language :: Python :: 3.8
Classifier: Programming Language :: Python :: 3.9
Classifier: Programming Language :: Python :: 3.10
Classifier: Programming Language :: Python :: 3.11
Classifier: Programming Language :: Python :: 3.12
Classifier: Topic :: Software Development :: Libraries :: Python Modules
Classifier: Topic :: Office/Business :: Financial
Classifier: Topic :: Scientific/Engineering :: Image Recognition
Requires-Python: >=3.8
Requires-Dist: requests>=2.25.0
Provides-Extra: dev
Requires-Dist: pytest>=7.0.0; extra == "dev"
Requires-Dist: pytest-cov>=4.0.0; extra == "dev"
Requires-Dist: black>=22.0.0; extra == "dev"
Requires-Dist: ruff>=0.1.0; extra == "dev"
Requires-Dist: mypy>=1.0.0; extra == "dev"
Requires-Dist: types-requests>=2.28.0; extra == "dev"
Dynamic: requires-python
